<?xml version="1.0"?>
<Page Version="4000" TimeStamp="2016-12-27 13:57:48">
	<Location top="30" left="30" bottom="540" right="600" />
	<PageEditSize Type="Inherited">
		<Size Width="600" Height="540" />
	</PageEditSize>
	<ProjectUUID>FD4E5DBD-7B49-4BC0-8952-143FD8233A59</ProjectUUID>
	<Title>"[Data Page] rMR"</Title>
	<ResizeData>
		<MainArea Line="FixedFromRight" Value="81">
			<LeftArea Line="FixedFromTop" Value="45" />
			<RightArea Line="FixedFromTop" Value="35">
				<BottomArea Line="FixedFromBottom" Value="106" />
			</RightArea>
		</MainArea>
	</ResizeData>
	<Background Inherited="true" />
	<PageObject Type="Button">
		<Location top="10" left="520" bottom="35" right="590" />
		<TabOrder>1</TabOrder>
		<LeaveOnEnter>false</LeaveOnEnter>
		<ButtonType>Text</ButtonType>
		<Title>"Close"</Title>
		<Font GUID="00000000-0000-0000-0000-000000000001" Name="Main Font" />
		<ActionSequence>
			<Action Type="ClosePage" />
		</ActionSequence>
	</PageObject>
	<PageObject Type="Button">
		<Location top="435" left="520" bottom="460" right="590" />
		<TabOrder>2</TabOrder>
		<LeaveOnEnter>false</LeaveOnEnter>
		<ButtonType>Text</ButtonType>
		<Title>"Undo"</Title>
		<Font GUID="00000000-0000-0000-0000-000000000001" Name="Main Font" />
		<ActionSequence>
			<Action Type="MenuCommand">
				<Command>Edit-Undo Last</Command>
			</Action>
		</ActionSequence>
	</PageObject>
	<PageObject Type="Button">
		<Location top="470" left="520" bottom="495" right="555" />
		<TabOrder>3</TabOrder>
		<LeaveOnEnter>false</LeaveOnEnter>
		<ButtonType>Bitmap</ButtonType>
		<BitmapFile LiteralFileName="true">"&lt;prj&gt;:bitmaps\construct.png"</BitmapFile>
		<Font GUID="00000000-0000-0000-0000-000000000001" Name="Main Font" />
		<ActionSequence>
			<Action Type="DataPageSpecific">
				<DoWhat>Reopen</DoWhat>
			</Action>
			<Action Type="ClosePage" />
		</ActionSequence>
	</PageObject>
	<PageObject Type="Button">
		<Location top="470" left="555" bottom="495" right="590" />
		<TabOrder>4</TabOrder>
		<LeaveOnEnter>false</LeaveOnEnter>
		<ButtonType>Bitmap</ButtonType>
		<BitmapFile LiteralFileName="true">"&lt;prj&gt;:bitmaps\totree.png"</BitmapFile>
		<Font GUID="00000000-0000-0000-0000-000000000001" Name="Main Font" />
		<ActionSequence>
			<Action Type="DataPageSpecific">
				<DoWhat>LocationInTree</DoWhat>
			</Action>
		</ActionSequence>
	</PageObject>
	<PageObject Type="Button">
		<Location top="505" left="520" bottom="530" right="555" />
		<TabOrder>5</TabOrder>
		<LeaveOnEnter>false</LeaveOnEnter>
		<ButtonType>Bitmap</ButtonType>
		<BitmapFile LiteralFileName="true">"&lt;prj&gt;:bitmaps\previous.png"</BitmapFile>
		<Font GUID="00000000-0000-0000-0000-000000000001" Name="Main Font" />
		<ActionSequence>
			<Action Type="DataPageSpecific">
				<DoWhat>GotoPreviousSymbol</DoWhat>
			</Action>
			<Action Type="ClosePage" />
		</ActionSequence>
	</PageObject>
	<PageObject Type="Button">
		<Location top="505" left="555" bottom="530" right="590" />
		<TabOrder>6</TabOrder>
		<LeaveOnEnter>false</LeaveOnEnter>
		<ButtonType>Bitmap</ButtonType>
		<BitmapFile LiteralFileName="true">"&lt;prj&gt;:bitmaps\next.png"</BitmapFile>
		<Font GUID="00000000-0000-0000-0000-000000000001" Name="Main Font" />
		<ActionSequence>
			<Action Type="DataPageSpecific">
				<DoWhat>GotoNextSymbol</DoWhat>
			</Action>
			<Action Type="ClosePage" />
		</ActionSequence>
	</PageObject>
	<PageObject Type="Floating Index">
		<Location top="10" left="10" bottom="35" right="110" />
		<TabOrder>7</TabOrder>
		<ObjectUUID>23A31ACD-85EB-4C93-852D-0B9ADAFD56B1</ObjectUUID>
		<Font GUID="00000000-0000-0000-0000-000000000001" Name="Main Font" />
		<Border Style="InShadow" Width="2" />
		<Circular>true</Circular>
		<ClickShowsList>true</ClickShowsList>
		<BackgroundColor RGB="#ffffff" />
		<Identifier>PlantGroup</Identifier>
	</PageObject>
	<PageObject Type="Scalar">
		<Location top="10" left="120" bottom="35" right="220" />
		<TabOrder>8</TabOrder>
		<PopupMenu Default="true" DefaultPopupId="200" />
		<Font GUID="00000000-0000-0000-0000-000000000001" Name="Main Font" />
		<Border Style="InShadow" Width="2" />
		<BackgroundColor RGB="#ffffff" />
		<Layout>Value</Layout>
		<SeparatorSign>=</SeparatorSign>
		<ExplicitIdentifier>
			<Identifier>rMR( '00020' )</Identifier>
			<IndexLinkage>[23A31ACD-85EB-4C93-852D-0B9ADAFD56B1]</IndexLinkage>
			<NumberFormat Width="5" Decimals="2" Scientific="IfTooSmallorLarge" Alignment="Center" ShowDefaults="true" />
		</ExplicitIdentifier>
	</PageObject>
	<PageObject Type="Composite Table">
		<Location top="45" left="10" bottom="530" right="510" />
		<TabOrder>9</TabOrder>
		<PopupMenu Default="true" DefaultPopupId="200" />
		<Font GUID="00000000-0000-0000-0000-000000000001" Name="Main Font" />
		<Border Style="InShadow" Width="2" />
		<BackgroundColor RGB="#ffffff" />
		<Domain>
			<Identifier>rMR( PlantGroup )</Identifier>
			<IndexLinkage>[23A31ACD-85EB-4C93-852D-0B9ADAFD56B1]</IndexLinkage>
			<Index Name="PlantGroup" />
			<AllowRowAdd>true</AllowRowAdd>
			<AllowRowDelete>true</AllowRowDelete>
			<AllowRowModify>true</AllowRowModify>
		</Domain>
		<ExplicitIdentifier>
			<Identifier>rMR( PlantGroup )</Identifier>
			<NumberFormat Width="10" Decimals="4" Alignment="Center" />
		</ExplicitIdentifier>
	</PageObject>
	<UsedReferences>
		<Model>
			<Symbol>rMR</Symbol>
			<Symbol>PlantGroup</Symbol>
		</Model>
	</UsedReferences>
</Page>
