<?xml version="1.0"?>
<Page Version="4000" TimeStamp="2020-08-18 00:13:43">
	<PageEditSize Type="Inherited" />
	<ProjectUUID>3C1E27EB-95CC-4E52-BBB5-D70269E0E21B</ProjectUUID>
	<TemplatesTabOrderPosition>1</TemplatesTabOrderPosition>
	<Background Inherited="true" />
	<Action>
		<EntryProcedure>CompareRuns</EntryProcedure>
	</Action>
	<PageObject Type="Pivot Table">
		<Location top="78" left="42" bottom="660" right="840" />
		<TabOrder>2</TabOrder>
		<ObjectUUID>843EF439-F9FB-4A24-A0F1-C819B4FCDB24</ObjectUUID>
		<Font GUID="00000000-0000-0000-0000-000000000001" Name="Main Font" />
		<Border Style="InShadow" Width="2" MarginTop="5" MarginRight="5" MarginBottom="5" MarginLeft="5" />
		<Contents>
			<Implicit_Identifiers ID="4010">IdentifierDiffSet( AllIdentifiers )</Implicit_Identifiers>
			<Defaults>
				<Format>
					<Decimal_Places ID="4212">2</Decimal_Places>
				</Format>
			</Defaults>
		</Contents>
		<Indices>
			<Identifier_Index>
				<Hide_if_Single_Identifier ID="6270">"No"</Hide_if_Single_Identifier>
			</Identifier_Index>
		</Indices>
		<General>
			<Multiple_Case_View ID="1020">"Yes"</Multiple_Case_View>
			<Dense_Aggregation_restricts_to_Domain ID="1022">"Yes"</Dense_Aggregation_restricts_to_Domain>
		</General>
		<Row_Area>
			<Background_Color ID="2010">RGB&lt;255,255,200&gt;</Background_Color>
			<Text_Color ExtraInfo="D4F48705-BFDF-4DF8-8E1F-D38EFF981024" ID="2020">"default selection"</Text_Color>
			<Headers>
				<Background_Color ExtraInfo="D4F48705-BFDF-4DF8-8E1F-D38EFF981024" ID="2120">"default selection"</Background_Color>
				<Text_Color ID="2130">RGB&lt;255,255,255&gt;</Text_Color>
				<Show_Sub_Headers ID="2150">"No"</Show_Sub_Headers>
			</Headers>
			<Grid_Focus_Indicator>
				<Background_Color ID="2270">RGB&lt;0,0,168&gt;</Background_Color>
				<Text_Color ID="2280">RGB&lt;255,255,200&gt;</Text_Color>
			</Grid_Focus_Indicator>
		</Row_Area>
		<Column_Area>
			<Auto_resize_Column_Widths ID="3006">"Upon all data changes"</Auto_resize_Column_Widths>
			<Headers>
				<Show_Sub_Headers ID="3150">"No"</Show_Sub_Headers>
			</Headers>
		</Column_Area>
		<Grid_Area>
			<Background_Color ID="5010">RGB&lt;255,255,255&gt;</Background_Color>
			<Alternating_Background_Color ID="5011">RGB&lt;225,225,225&gt;</Alternating_Background_Color>
			<Aggregators>
				<Background_Color ID="5220">RGB&lt;255,128,128&gt;</Background_Color>
			</Aggregators>
			<Sub_Header_Row_or_Column>
				<Background_Color ID="5320">RGB&lt;255,255,200&gt;</Background_Color>
			</Sub_Header_Row_or_Column>
		</Grid_Area>
	</PageObject>
	<UsedReferences>
		<Model>
			<Symbol>AllIdentifiers</Symbol>
			<Symbol>IdentifierDiffSet</Symbol>
			<Symbol>CompareRuns</Symbol>
		</Model>
	</UsedReferences>
</Page>
